docnav/__init__.py
docnav/cli.py
docnav/core.py
docnav/handlers.py
docnav-1.0.1.dist-info/licenses/LICENSE
docnav-1.0.1.dist-info/METADATA
docnav-1.0.1.dist-info/WHEEL
docnav-1.0.1.dist-info/entry_points.txt
docnav-1.0.1.dist-info/top_level.txt
docnav-1.0.1.dist-info/RECORD
