Metadata-Version: 2.4
Name: docnav
Version: 1.0.1
Summary: AI-powered document querying with citations
Home-page: https://github.com/ailaysa/docnav
Author: Mukesh Anand G
Author-email: Mukesh Anand G <ai.mukeshanandg@gmail.com>
Maintainer-email: Mukesh Anand G <ai.mukeshanandg@gmail.com>
License: MIT
Project-URL: Homepage, https://github.com/Mukesh-Anand-G/DocNav
Keywords: document processing,RAG,ai,llm,search,query,rag,retrieval augmented generation,document management,text analysis,citations,openai,gemini,claude
Classifier: Development Status :: 5 - Production/Stable
Classifier: Intended Audience :: Developers
Classifier: Intended Audience :: End Users/Desktop
Classifier: License :: OSI Approved :: MIT License
Classifier: Operating System :: OS Independent
Classifier: Programming Language :: Python :: 3
Classifier: Programming Language :: Python :: 3.8
Classifier: Programming Language :: Python :: 3.9
Classifier: Programming Language :: Python :: 3.10
Classifier: Programming Language :: Python :: 3.11
Classifier: Programming Language :: Python :: 3.12
Classifier: Programming Language :: Python :: 3.13
Classifier: Topic :: Scientific/Engineering :: Artificial Intelligence
Classifier: Topic :: Text Processing :: Indexing
Classifier: Topic :: Text Processing :: Linguistic
Requires-Python: >=3.8
License-File: LICENSE
Requires-Dist: numpy>=1.21.0
Requires-Dist: tqdm>=4.62.0
Requires-Dist: pathlib2>=2.3.6; python_version < "3.4"
Provides-Extra: full
Requires-Dist: sentence-transformers>=2.0.0; extra == "full"
Requires-Dist: python-docx>=0.8.11; extra == "full"
Requires-Dist: PyPDF2>=3.0.0; extra == "full"
Requires-Dist: pandas>=1.3.0; extra == "full"
Requires-Dist: python-pptx>=0.6.21; extra == "full"
Requires-Dist: openai>=1.0.0; extra == "full"
Requires-Dist: google-generativeai>=0.3.0; extra == "full"
Requires-Dist: anthropic>=0.8.0; extra == "full"
Provides-Extra: ocr
Requires-Dist: pdf2image>=1.16.0; extra == "ocr"
Requires-Dist: pytesseract>=0.3.10; extra == "ocr"
Provides-Extra: dev
Requires-Dist: pytest>=7.0.0; extra == "dev"
Requires-Dist: black>=22.0.0; extra == "dev"
Requires-Dist: flake8>=4.0.0; extra == "dev"
Requires-Dist: mypy>=0.991; extra == "dev"
Dynamic: author
Dynamic: home-page
Dynamic: license-file
Dynamic: requires-python
